nonebot_plugin_fakemsg-0.1.9.dist-info/METADATA
nonebot_plugin_fakemsg-0.1.9.dist-info/WHEEL
nonebot_plugin_fakemsg-0.1.9.dist-info/entry_points.txt
nonebot_plugin_fakemsg-0.1.9.dist-info/licenses/LICENSE
nonebot_plugin_fakemsg/__init__.py
nonebot_plugin_fakemsg/config.py
nonebot_plugin_fakemsg-0.1.9.dist-info/RECORD
