Metadata-Version: 2.1
Name: nonebot-plugin-fakemsg
Version: 0.1.9
Summary: 适用于onebot的伪消息插件
Author-Email: Cvandia <106718176+Cvandia@users.noreply.github.com>
License: MIT
Requires-Python: <4,>=3.8
Requires-Dist: nonebot-adapter-onebot>=2.0.0-beta.1
Requires-Dist: nonebot2>=2.0.0-beta.1
